fast_grid/__init__.py
fast_grid/calculate_grid.py
fast_grid/ff.py
fast_grid/potential.py
fast_grid/utils.py
fast_grid/visualize.py
fast_grid/assets/uff_ff.csv
fast_grid-0.2.0.dist-info/METADATA
fast_grid-0.2.0.dist-info/WHEEL
fast_grid-0.2.0.dist-info/entry_points.txt
fast_grid-0.2.0.dist-info/top_level.txt
fast_grid-0.2.0.dist-info/RECORD
