Metadata-Version: 2.1
Name: fast-grid
Version: 0.2.0
Summary: Fast grid calculation
Home-page: https://github.com/hspark1212/fast-grid.git
Author: Hyunsoo Park
Author-email: phs68660888@gmail.com
Requires-Python: >=3.9
Requires-Dist: ase
Requires-Dist: numba
Requires-Dist: fire
Requires-Dist: pandas
Requires-Dist: plotly
Requires-Dist: ipykernel
Requires-Dist: nbformat
Requires-Dist: MDAnalysis
